CHANGELOG.txt
LICENCE.txt
MANIFEST.in
README.txt
setup.py
csvlibprocessflow.egg-info/PKG-INFO
csvlibprocessflow.egg-info/SOURCES.txt
csvlibprocessflow.egg-info/dependency_links.txt
csvlibprocessflow.egg-info/requires.txt
csvlibprocessflow.egg-info/top_level.txt
csvlibpy/__init__.py