Metadata-Version: 1.1
Name: csvlibprocessflow
Version: 0.0.1
Summary: creating xls from user input in databricks
Home-page: UNKNOWN
Author: Bhavsik
Author-email: bbhadarka@infosenseglobal.com
License: MIT
Platform: UNKNOWN
Classifier: Development Status :: 1 - Planning
Classifier: Intended Audience :: Education
Classifier: Operating System :: Microsoft :: Windows :: Windows 10
Classifier: License :: OSI Approved :: MIT License
Classifier: Programming Language :: Python :: 3
